djaffar/__init__.py
djaffar/admin.py
djaffar/apps.py
djaffar/models.py
djaffar/tests.py
djaffar/urls.py
djaffar/views.py
djaffar/__pycache__/__init__.cpython-35.pyc
djaffar/__pycache__/__init__.cpython-36.pyc
djaffar/__pycache__/models.cpython-35.pyc
djaffar/__pycache__/models.cpython-36.pyc
djaffar/__pycache__/urls.cpython-35.pyc
djaffar/__pycache__/urls.cpython-36.pyc
djaffar/__pycache__/views.cpython-35.pyc
djaffar/__pycache__/views.cpython-36.pyc
djaffar/migrations/0001_initial.py
djaffar/migrations/__init__.py
djaffar/migrations/__pycache__/0001_initial.cpython-35.pyc
djaffar/migrations/__pycache__/0001_initial.cpython-36.pyc
djaffar/migrations/__pycache__/__init__.cpython-35.pyc
djaffar/migrations/__pycache__/__init__.cpython-36.pyc
django_djaffar-0.1.10.dist-info/DESCRIPTION.rst
django_djaffar-0.1.10.dist-info/METADATA
django_djaffar-0.1.10.dist-info/RECORD
django_djaffar-0.1.10.dist-info/WHEEL
django_djaffar-0.1.10.dist-info/metadata.json
django_djaffar-0.1.10.dist-info/top_level.txt
