Metadata-Version: 2.0
Name: django-djaffar
Version: 0.1.10
Summary: An asynchronous user activity tracking API for Django.
Home-page: https://github.com/arnaudrenaud/django-djaffar
Author: Arnaud Renaud
Author-email: arnaud.renaud@gmail.com
License: BSD License
Download-URL: https://github.com/arnaudrenaud/django-djaffar/tarball/0.1.10
Platform: UNKNOWN
Classifier: Development Status :: 3 - Alpha
Classifier: Environment :: Web Environment
Classifier: Framework :: Django
Classifier: Framework :: Django :: 1.8
Classifier: Framework :: Django :: 1.9
Classifier: Framework :: Django :: 1.10
Classifier: Intended Audience :: Developers
Classifier: License :: OSI Approved :: BSD License
Classifier: Operating System :: OS Independent
Classifier: Natural Language :: English
Classifier: Programming Language :: Python :: 2
Classifier: Programming Language :: Python :: 2.7
Classifier: Programming Language :: Python :: 3
Classifier: Programming Language :: Python :: 3.3
Classifier: Programming Language :: Python :: 3.4
Classifier: Programming Language :: Python :: 3.5
Classifier: Topic :: Internet :: WWW/HTTP
Requires-Dist: Django (>=1.8)
Requires-Dist: djangorestframework (>=3.3)
Requires-Dist: python-dateutil (>=2.6)
